aidk/__init__.py
aidk/agents/__init__.py
aidk/agents/agent.py
aidk/agents/agentic_loop.py
aidk/agents/agentic_loops/__init__.py
aidk/agents/agentic_loops/_agentic_loop.py
aidk/agents/agentic_loops/_function_calling_agentic_loop.py
aidk/agents/agentic_loops/_other_agentic_loops.py
aidk/agents/agentic_loops/_react_agentic_loop.py
aidk/application/__init__.py
aidk/application/application.py
aidk/application/rate_limiter.py
aidk/chat/__init__.py
aidk/chat/chat.py
aidk/chat/history/__init__.py
aidk/chat/history/dict_history.py
aidk/chat/history/firestore_history.py
aidk/chat/history/json_history.py
aidk/chat/history/models.py
aidk/chat/history/mongodb_history.py
aidk/chat/history/sqlite_history.py
aidk/chat/history/summarizer.py
aidk/cli/__init__.py
aidk/conf/__init__.py
aidk/conf/conf.py
aidk/keys/keys_manager.py
aidk/mcp/__init__.py
aidk/mcp/_mcp_tool_parser.py
aidk/mcp/mcp_server.py
aidk/models/__init__.py
aidk/models/_base_model.py
aidk/models/_prompt_executor.py
aidk/models/_response_processor.py
aidk/models/auto_model.py
aidk/models/hosted_model.py
aidk/models/image_model.py
aidk/models/model.py
aidk/models/voice_model.py
aidk/observability/__init__.py
aidk/prompts/__init__.py
aidk/prompts/fewshot_prompt.py
aidk/prompts/meta_prompt.py
aidk/prompts/prompt.py
aidk/prompts/prompt_chain.py
aidk/prompts/safe_prompt.py
aidk/prompts/system_prompt.py
aidk/rag/__init__.py
aidk/rag/rag.py
aidk/rag/documents_builder/__init__.py
aidk/rag/documents_builder/base.py
aidk/rag/documents_builder/builder.py
aidk/rag/documents_builder/extractors.py
aidk/rag/documents_builder/splitters.py
aidk/rag/vectordb/__init__.py
aidk/rag/vectordb/base.py
aidk/rag/vectordb/chroma.py
aidk/tests/test_agent.py
aidk/tests/test_chat.py
aidk/tests/test_model.py
aidk/tokens/__init__.py
aidk/tokens/token_cost.py
aidk/tokens/token_counter.py
aidk/tokens/token_pricing.py
aidk/tools/__init__.py
aidk/tools/_tool_parser.py
aidk/tools/browser_use.py
aidk/tools/colab_downloader.py
aidk/tools/computer_use.py
aidk_python-0.0.2.dist-info/licenses/LICENSE
aidk_python-0.0.2.dist-info/METADATA
aidk_python-0.0.2.dist-info/WHEEL
aidk_python-0.0.2.dist-info/entry_points.txt
aidk_python-0.0.2.dist-info/top_level.txt
aidk_python-0.0.2.dist-info/RECORD
